setup.py
drf_ujson/__init__.py
drf_ujson/parsers.py
drf_ujson/renderers.py
drf_ujson.egg-info/PKG-INFO
drf_ujson.egg-info/SOURCES.txt
drf_ujson.egg-info/dependency_links.txt
drf_ujson.egg-info/requires.txt
drf_ujson.egg-info/top_level.txt