Metadata-Version: 1.0
Name: drf-ujson
Version: 1.2
Summary: Django Rest Framework UJSON Renderer
Home-page: https://github.com/gizmag/drf-ujson-renderer
Author: Gizmag
Author-email: tech@gizmag.com
License: UNKNOWN
Platform: UNKNOWN
